snvis/__init__.py
snvis/__main__.py
snvis/_version.py
snvis/cli.py
snvis/driver.py
snvis/log.py
snvis/cli/__init__.py
snvis/cli/__main__.py
snvis/core/__init__.py
snvis/core/_version.py
snvis/core/graphing.py
snvis/core/parsing.py
snvis/core/pyvis.py
snvis-0.1.12.dist-info/LICENSE
snvis-0.1.12.dist-info/METADATA
snvis-0.1.12.dist-info/WHEEL
snvis-0.1.12.dist-info/entry_points.txt
snvis-0.1.12.dist-info/top_level.txt
snvis-0.1.12.dist-info/RECORD
